[
  {
    "code": "US0010841023",
    "name": "AGCO CORP",
    "amount": "58.23",
    "price": "",
    "ratio": "",
    "totalPrice": ""
  },
  {
    "code": "US0394831020",
    "name": "ARCHER-DANIELS-MIDLAND CO",
    "amount": "274.92",
    "price": "",
    "ratio": "",
    "totalPrice": ""
  },
  {
    "code": "FO0000000179",
    "name": "BAKKAFROST P/F",
    "amount": "53.16",
    "price": "",
    "ratio": "",
    "totalPrice": ""
  },
  {
    "code": "US0576652004",
    "name": "BALCHEM CORP",
    "amount": "22.32",
    "price": "",
    "ratio": "",
    "totalPrice": ""
  },
  {
    "code": "DE000BAY0017",
    "name": "BAYER AG-REG",
    "amount": "671.68",
    "price": "",
    "ratio": "",
    "totalPrice": ""
  },
  {
    "code": "CH0002432174",
    "name": "BUCHER INDUSTRIES AG-REG",
    "amount": "8.01",
    "price": "",
    "ratio": "",
    "totalPrice": ""
  },
  {
    "code": "CH1300646267",
    "name": "BUNGE GLOBAL SA",
    "amount": "127.92",
    "price": "",
    "ratio": "",
    "totalPrice": ""
  },
  {
    "code": "US1252691001",
    "name": "CF INDUSTRIES HOLDINGS INC",
    "amount": "153.59",
    "price": "",
    "ratio": "",
    "totalPrice": ""
  },
  {
    "code": "KYG210961051",
    "name": "CHINA MENGNIU DAIRY CO",
    "amount": "1623.15",
    "price": "",
    "ratio": "",
    "totalPrice": ""
  },
  {
    "code": "NL0010545661",
    "name": "CNH INDUSTRIAL NV",
    "amount": "1022.99",
    "price": "",
    "ratio": "",
    "totalPrice": ""
  },
  {
    "code": "US22052L1044",
    "name": "CORTEVA INC",
    "amount": "417.76",
    "price": "",
    "ratio": "",
    "totalPrice": ""
  },
  {
    "code": "US2372661015",
    "name": "DARLING INGREDIENTS INC",
    "amount": "144.97",
    "price": "",
    "ratio": "",
    "totalPrice": ""
  },
  {
    "code": "US2441991054",
    "name": "DEERE & CO",
    "amount": "73.45",
    "price": "",
    "ratio": "",
    "totalPrice": ""
  },
  {
    "code": "US28414H1032",
    "name": "ELANCO ANIMAL HEALTH INC",
    "amount": "361.66",
    "price": "",
    "ratio": "",
    "totalPrice": ""
  },
  {
    "code": "US3024913036",
    "name": "FMC CORP",
    "amount": "104.69",
    "price": "",
    "ratio": "",
    "totalPrice": ""
  },
  {
    "code": "GB0002074580",
    "name": "GENUS PLC",
    "amount": "48.49",
    "price": "",
    "ratio": "",
    "totalPrice": ""
  },
  {
    "code": "MU0117U00026",
    "name": "GOLDEN AGRI-RESOURCES LTD",
    "amount": "5457.85",
    "price": "",
    "ratio": "",
    "totalPrice": ""
  },
  {
    "code": "IL0002810146",
    "name": "ICL GROUP LTD",
    "amount": "616.90",
    "price": "",
    "ratio": "",
    "totalPrice": ""
  },
  {
    "code": "AU000000IPL1",
    "name": "INCITEC PIVOT LTD",
    "amount": "1832.74",
    "price": "",
    "ratio": "",
    "totalPrice": ""
  },
  {
    "code": "DE000KSAG888",
    "name": "K+S AG-REG",
    "amount": "222.98",
    "price": "",
    "ratio": "",
    "totalPrice": ""
  },
  {
    "code": "JP3266400005",
    "name": "KUBOTA CORP",
    "amount": "862.30",
    "price": "",
    "ratio": "",
    "totalPrice": ""
  },
  {
    "code": "NO0003096208",
    "name": "LEROY SEAFOOD GROUP ASA",
    "amount": "326.15",
    "price": "",
    "ratio": "",
    "totalPrice": ""
  },
  {
    "code": "JP3876600002",
    "name": "MARUHA NICHIRO CORP",
    "amount": "50.72",
    "price": "",
    "ratio": "",
    "totalPrice": ""
  },
  {
    "code": "US61945C1036",
    "name": "MOSAIC CO/THE",
    "amount": "228.46",
    "price": "",
    "ratio": "",
    "totalPrice": ""
  },
  {
    "code": "NO0003054108",
    "name": "MOWI ASA",
    "amount": "475.89",
    "price": "",
    "ratio": "",
    "totalPrice": ""
  },
  {
    "code": "US6404911066",
    "name": "NEOGEN CORP",
    "amount": "163.84",
    "price": "",
    "ratio": "",
    "totalPrice": ""
  },
  {
    "code": "JP3743000006",
    "name": "NH FOODS LTD",
    "amount": "101.45",
    "price": "",
    "ratio": "",
    "totalPrice": ""
  },
  {
    "code": "JP3718800000",
    "name": "NISSUI CORP",
    "amount": "273.91",
    "price": "",
    "ratio": "",
    "totalPrice": ""
  },
  {
    "code": "CA67077M1086",
    "name": "NUTRIEN LTD",
    "amount": "408.32",
    "price": "",
    "ratio": "",
    "totalPrice": ""
  },
  {
    "code": "NL0010558797",
    "name": "OCI NV",
    "amount": "127.82",
    "price": "",
    "ratio": "",
    "totalPrice": ""
  },
  {
    "code": "US72147K1088",
    "name": "PILGRIMS PRIDE CORP",
    "amount": "48.19",
    "price": "",
    "ratio": "",
    "totalPrice": ""
  },
  {
    "code": "US8336351056",
    "name": "QUIMICA Y MINERA CHIL-SP ADR",
    "amount": "59.85",
    "price": "",
    "ratio": "",
    "totalPrice": ""
  },
  {
    "code": "BRRAILACNOR9",
    "name": "RUMO SA",
    "amount": "1339.10",
    "price": "",
    "ratio": "",
    "totalPrice": ""
  },
  {
    "code": "NO0010310956",
    "name": "SALMAR ASA",
    "amount": "82.88",
    "price": "",
    "ratio": "",
    "totalPrice": ""
  },
  {
    "code": "DK0010253921",
    "name": "SCHOUW & CO",
    "amount": "14.91",
    "price": "",
    "ratio": "",
    "totalPrice": ""
  },
  {
    "code": "US8910921084",
    "name": "TORO CO",
    "amount": "83.49",
    "price": "",
    "ratio": "",
    "totalPrice": ""
  },
  {
    "code": "AU000000TWE9",
    "name": "TREASURY WINE ESTATES LTD",
    "amount": "682.13",
    "price": "",
    "ratio": "",
    "totalPrice": ""
  },
  {
    "code": "US9024941034",
    "name": "TYSON FOODS INC-CL A",
    "amount": "259.20",
    "price": "",
    "ratio": "",
    "totalPrice": ""
  },
  {
    "code": "SG1T56930848",
    "name": "WILMAR INTERNATIONAL LTD",
    "amount": "3631.81",
    "price": "",
    "ratio": "",
    "totalPrice": ""
  },
  {
    "code": "NO0010208051",
    "name": "YARA INTERNATIONAL ASA",
    "amount": "169.11",
    "price": "",
    "ratio": "",
    "totalPrice": ""
  },
  {
    "code": "US98978V1035",
    "name": "ZOETIS INC",
    "amount": "147.40",
    "price": "",
    "ratio": "",
    "totalPrice": ""
  },
  {
    "code": "KRD010010001",
    "name": "원화현금",
    "amount": "",
    "price": "3809037",
    "ratio": "",
    "totalPrice": ""
  },
  {
    "code": "CASH00000001",
    "name": "설정현금액",
    "amount": "",
    "price": "442467781",
    "ratio": "",
    "totalPrice": ""
  }
]