[
  {
    "code": "HK0000123577",
    "name": "CHINAAMC ETF SERIES - CH-HKD",
    "amount": "600.00",
    "price": "",
    "ratio": "",
    "totalPrice": "3862425"
  },
  {
    "code": "KRYZTRSD1201",
    "name": "차이나CSI300 TRS(미래에셋증권)",
    "amount": "54294012.42",
    "price": "",
    "ratio": "",
    "totalPrice": "54294012"
  },
  {
    "code": "KRYZTRSC8A13",
    "name": "차이나CSI300 TRS(삼성증권)",
    "amount": "3443278.33",
    "price": "",
    "ratio": "",
    "totalPrice": "3443278"
  },
  {
    "code": "KRYZTRSC8A12",
    "name": "차이나CSI300 TRS(키움증권)",
    "amount": "8932562.69",
    "price": "",
    "ratio": "",
    "totalPrice": "8932562"
  },
  {
    "code": "KRD010010001",
    "name": "원화현금",
    "amount": "",
    "price": "408278579",
    "ratio": "",
    "totalPrice": ""
  },
  {
    "code": "CASH00000001",
    "name": "설정현금액",
    "amount": "",
    "price": "478810856",
    "ratio": "",
    "totalPrice": ""
  }
]