[
  {
    "code": "005930",
    "name": "삼성전자",
    "amount": "2931.00",
    "price": "213376800",
    "ratio": "25.26",
    "totalPrice": "213083700"
  },
  {
    "code": "000660",
    "name": "SK하이닉스",
    "amount": "1460.00",
    "price": "195494000",
    "ratio": "23.14",
    "totalPrice": "190384000"
  },
  {
    "code": "005490",
    "name": "POSCO홀딩스",
    "amount": "170.00",
    "price": "82110000",
    "ratio": "9.72",
    "totalPrice": "82110000"
  },
  {
    "code": "005380",
    "name": "현대차",
    "amount": "424.00",
    "price": "78143200",
    "ratio": "9.25",
    "totalPrice": "78355200"
  },
  {
    "code": "051910",
    "name": "LG화학",
    "amount": "142.00",
    "price": "71142000",
    "ratio": "8.42",
    "totalPrice": "71568000"
  },
  {
    "code": "000270",
    "name": "기아",
    "amount": "813.00",
    "price": "69836700",
    "ratio": "8.27",
    "totalPrice": "69918000"
  },
  {
    "code": "105560",
    "name": "KB금융",
    "amount": "809.00",
    "price": "42391600",
    "ratio": "5.02",
    "totalPrice": "41825300"
  },
  {
    "code": "055550",
    "name": "신한지주",
    "amount": "1013.00",
    "price": "37379700",
    "ratio": "4.43",
    "totalPrice": "36771900"
  },
  {
    "code": "086790",
    "name": "하나금융지주",
    "amount": "594.00",
    "price": "24740100",
    "ratio": "2.93",
    "totalPrice": "24502500"
  },
  {
    "code": "316140",
    "name": "우리금융지주",
    "amount": "1460.00",
    "price": "19009200",
    "ratio": "2.25",
    "totalPrice": "18688000"
  },
  {
    "code": "KRD010010001",
    "name": "원화현금",
    "amount": "",
    "price": "11064264",
    "ratio": "1.31",
    "totalPrice": ""
  }
]