[
  {
    "code": "KR4167TC0009",
    "name": "10년국채   F 202312",
    "amount": "1.17",
    "price": "",
    "ratio": "",
    "totalPrice": "132982200"
  },
  {
    "code": "KR4167V30006",
    "name": "10년국채   F 202403",
    "amount": "2.30",
    "price": "",
    "ratio": "",
    "totalPrice": "261970000"
  },
  {
    "code": "KRD010010001",
    "name": "원화현금",
    "amount": "",
    "price": "395018203",
    "ratio": "",
    "totalPrice": ""
  },
  {
    "code": "CASH00000001",
    "name": "설정현금액",
    "amount": "",
    "price": "395018203",
    "ratio": "",
    "totalPrice": ""
  }
]