[
  {
    "code": "139280",
    "name": "TIGER 경기방어",
    "amount": "11300.00",
    "price": "106389500",
    "ratio": "",
    "totalPrice": "110062000"
  },
  {
    "code": "068270",
    "name": "셀트리온",
    "amount": "262.00",
    "price": "56723000",
    "ratio": "",
    "totalPrice": "60653000"
  },
  {
    "code": "114820",
    "name": "TIGER 국채3년",
    "amount": "525.00",
    "price": "55883625",
    "ratio": "",
    "totalPrice": "55794375"
  },
  {
    "code": "207940",
    "name": "삼성바이오로직스",
    "amount": "25.00",
    "price": "19150000",
    "ratio": "",
    "totalPrice": "19675000"
  },
  {
    "code": "033780",
    "name": "KT&G",
    "amount": "157.00",
    "price": "14114300",
    "ratio": "",
    "totalPrice": "14114300"
  },
  {
    "code": "030200",
    "name": "KT",
    "amount": "347.00",
    "price": "11589800",
    "ratio": "",
    "totalPrice": "11659200"
  },
  {
    "code": "017670",
    "name": "SK텔레콤",
    "amount": "233.00",
    "price": "11498550",
    "ratio": "",
    "totalPrice": "11498550"
  },
  {
    "code": "015760",
    "name": "한국전력",
    "amount": "486.00",
    "price": "9243720",
    "ratio": "",
    "totalPrice": "9355500"
  },
  {
    "code": "090430",
    "name": "아모레퍼시픽",
    "amount": "48.00",
    "price": "6307200",
    "ratio": "",
    "totalPrice": "6465600"
  },
  {
    "code": "000100",
    "name": "유한양행",
    "amount": "94.00",
    "price": "6260400",
    "ratio": "",
    "totalPrice": "6467200"
  },
  {
    "code": "051900",
    "name": "LG생활건강",
    "amount": "14.00",
    "price": "4704000",
    "ratio": "",
    "totalPrice": "4767000"
  },
  {
    "code": "032640",
    "name": "LG유플러스",
    "amount": "432.00",
    "price": "4350240",
    "ratio": "",
    "totalPrice": "4376160"
  },
  {
    "code": "128940",
    "name": "한미약품",
    "amount": "12.00",
    "price": "4314000",
    "ratio": "",
    "totalPrice": "4398000"
  },
  {
    "code": "326030",
    "name": "SK바이오팜",
    "amount": "42.00",
    "price": "4061400",
    "ratio": "",
    "totalPrice": "4363800"
  },
  {
    "code": "271560",
    "name": "오리온",
    "amount": "34.00",
    "price": "3933800",
    "ratio": "",
    "totalPrice": "3964400"
  },
  {
    "code": "097950",
    "name": "CJ제일제당",
    "amount": "12.00",
    "price": "3840000",
    "ratio": "",
    "totalPrice": "3786000"
  },
  {
    "code": "302440",
    "name": "SK바이오사이언스",
    "amount": "33.00",
    "price": "2333100",
    "ratio": "",
    "totalPrice": "2405700"
  },
  {
    "code": "139480",
    "name": "이마트",
    "amount": "31.00",
    "price": "2253700",
    "ratio": "",
    "totalPrice": "2284700"
  },
  {
    "code": "009420",
    "name": "한올바이오파마",
    "amount": "55.00",
    "price": "2202750",
    "ratio": "",
    "totalPrice": "2321000"
  },
  {
    "code": "004370",
    "name": "농심",
    "amount": "5.00",
    "price": "2052500",
    "ratio": "",
    "totalPrice": "2052500"
  },
  {
    "code": "001040",
    "name": "CJ",
    "amount": "21.00",
    "price": "1963500",
    "ratio": "",
    "totalPrice": "1978200"
  },
  {
    "code": "008930",
    "name": "한미사이언스",
    "amount": "45.00",
    "price": "1705500",
    "ratio": "",
    "totalPrice": "1797750"
  },
  {
    "code": "185750",
    "name": "종근당",
    "amount": "13.00",
    "price": "1644500",
    "ratio": "",
    "totalPrice": "1684800"
  },
  {
    "code": "282330",
    "name": "BGF리테일",
    "amount": "12.00",
    "price": "1633200",
    "ratio": "",
    "totalPrice": "1647600"
  },
  {
    "code": "007070",
    "name": "GS리테일",
    "amount": "65.00",
    "price": "1527500",
    "ratio": "",
    "totalPrice": "1517750"
  },
  {
    "code": "192820",
    "name": "코스맥스",
    "amount": "12.00",
    "price": "1378800",
    "ratio": "",
    "totalPrice": "1388400"
  },
  {
    "code": "161890",
    "name": "한국콜마",
    "amount": "25.00",
    "price": "1327500",
    "ratio": "",
    "totalPrice": "1325000"
  },
  {
    "code": "003230",
    "name": "삼양식품",
    "amount": "6.00",
    "price": "1320000",
    "ratio": "",
    "totalPrice": "1305000"
  },
  {
    "code": "036460",
    "name": "한국가스공사",
    "amount": "50.00",
    "price": "1227500",
    "ratio": "",
    "totalPrice": "1232500"
  },
  {
    "code": "002790",
    "name": "아모레G",
    "amount": "41.00",
    "price": "1102900",
    "ratio": "",
    "totalPrice": "1141850"
  },
  {
    "code": "000080",
    "name": "하이트진로",
    "amount": "48.00",
    "price": "1075200",
    "ratio": "",
    "totalPrice": "1080000"
  },
  {
    "code": "006280",
    "name": "녹십자",
    "amount": "8.00",
    "price": "979200",
    "ratio": "",
    "totalPrice": "1014400"
  },
  {
    "code": "004990",
    "name": "롯데지주",
    "amount": "37.00",
    "price": "950900",
    "ratio": "",
    "totalPrice": "956450"
  },
  {
    "code": "026960",
    "name": "동서",
    "amount": "48.00",
    "price": "827040",
    "ratio": "",
    "totalPrice": "843840"
  },
  {
    "code": "069620",
    "name": "대웅제약",
    "amount": "7.00",
    "price": "798700",
    "ratio": "",
    "totalPrice": "822500"
  },
  {
    "code": "007310",
    "name": "오뚜기",
    "amount": "2.00",
    "price": "788000",
    "ratio": "",
    "totalPrice": "792000"
  },
  {
    "code": "005300",
    "name": "롯데칠성",
    "amount": "5.00",
    "price": "737500",
    "ratio": "",
    "totalPrice": "739500"
  },
  {
    "code": "019170",
    "name": "신풍제약",
    "amount": "53.00",
    "price": "710200",
    "ratio": "",
    "totalPrice": "737760"
  },
  {
    "code": "137310",
    "name": "에스디바이오센서",
    "amount": "56.00",
    "price": "642880",
    "ratio": "",
    "totalPrice": "654080"
  },
  {
    "code": "003090",
    "name": "대웅",
    "amount": "30.00",
    "price": "612000",
    "ratio": "",
    "totalPrice": "628500"
  },
  {
    "code": "001680",
    "name": "대상",
    "amount": "29.00",
    "price": "594500",
    "ratio": "",
    "totalPrice": "590150"
  },
  {
    "code": "005250",
    "name": "녹십자홀딩스",
    "amount": "34.00",
    "price": "553180",
    "ratio": "",
    "totalPrice": "573920"
  },
  {
    "code": "001800",
    "name": "오리온홀딩스",
    "amount": "32.00",
    "price": "450880",
    "ratio": "",
    "totalPrice": "452160"
  },
  {
    "code": "280360",
    "name": "롯데웰푸드",
    "amount": "3.00",
    "price": "388800",
    "ratio": "",
    "totalPrice": "375000"
  },
  {
    "code": "KR4165V30000",
    "name": "3년국채    F 202403",
    "amount": "0.38",
    "price": "",
    "ratio": "",
    "totalPrice": "39858200"
  },
  {
    "code": "KR103501GC66",
    "name": "국고채권03125-2506(22-4)",
    "amount": "",
    "price": "",
    "ratio": "",
    "totalPrice": "180000000"
  },
  {
    "code": "KR103501GD99",
    "name": "국고채권03500-2809(23-6)",
    "amount": "",
    "price": "",
    "ratio": "",
    "totalPrice": "183479400"
  },
  {
    "code": "KR103501GCC0",
    "name": "국고채권04250-2512(22-13)",
    "amount": "",
    "price": "",
    "ratio": "",
    "totalPrice": "183541140"
  },
  {
    "code": "KRD010010001",
    "name": "원화현금",
    "amount": "",
    "price": "14118914",
    "ratio": "",
    "totalPrice": ""
  }
]