[
  {
    "code": "000660",
    "name": "SK하이닉스",
    "amount": "606.00",
    "price": "79446600",
    "ratio": "28.16",
    "totalPrice": "78719400"
  },
  {
    "code": "005930",
    "name": "삼성전자",
    "amount": "843.00",
    "price": "61454700",
    "ratio": "21.78",
    "totalPrice": "61117500"
  },
  {
    "code": "006400",
    "name": "삼성SDI",
    "amount": "75.00",
    "price": "34537500",
    "ratio": "12.24",
    "totalPrice": "33300000"
  },
  {
    "code": "066570",
    "name": "LG전자",
    "amount": "245.00",
    "price": "26068000",
    "ratio": "9.24",
    "totalPrice": "25896500"
  },
  {
    "code": "003550",
    "name": "LG",
    "amount": "211.00",
    "price": "17998300",
    "ratio": "6.38",
    "totalPrice": "17998300"
  },
  {
    "code": "009150",
    "name": "삼성전기",
    "amount": "125.00",
    "price": "17375000",
    "ratio": "6.16",
    "totalPrice": "17425000"
  },
  {
    "code": "018260",
    "name": "삼성에스디에스",
    "amount": "86.00",
    "price": "12547400",
    "ratio": "4.45",
    "totalPrice": "12693600"
  },
  {
    "code": "402340",
    "name": "SK스퀘어",
    "amount": "222.00",
    "price": "10422900",
    "ratio": "3.69",
    "totalPrice": "10789200"
  },
  {
    "code": "011070",
    "name": "LG이노텍",
    "amount": "32.00",
    "price": "8000000",
    "ratio": "2.84",
    "totalPrice": "7968000"
  },
  {
    "code": "034220",
    "name": "LG디스플레이",
    "amount": "513.00",
    "price": "7002450",
    "ratio": "2.48",
    "totalPrice": "6981930"
  },
  {
    "code": "000990",
    "name": "DB하이텍",
    "amount": "80.00",
    "price": "4464000",
    "ratio": "1.58",
    "totalPrice": "4424000"
  },
  {
    "code": "020150",
    "name": "롯데에너지머티리얼즈",
    "amount": "46.00",
    "price": "1966500",
    "ratio": "0.70",
    "totalPrice": "1902100"
  },
  {
    "code": "KRD010010001",
    "name": "원화현금",
    "amount": "",
    "price": "874658",
    "ratio": "0.31",
    "totalPrice": ""
  }
]