[
  {
    "code": "086900",
    "name": "메디톡스",
    "amount": "212.00",
    "price": "50668000",
    "ratio": "10.71",
    "totalPrice": "49502000"
  },
  {
    "code": "145720",
    "name": "덴티움",
    "amount": "382.00",
    "price": "48246600",
    "ratio": "10.20",
    "totalPrice": "47406200"
  },
  {
    "code": "145020",
    "name": "휴젤",
    "amount": "300.00",
    "price": "44700000",
    "ratio": "9.45",
    "totalPrice": "44310000"
  },
  {
    "code": "214450",
    "name": "파마리서치",
    "amount": "371.00",
    "price": "41737500",
    "ratio": "8.83",
    "totalPrice": "40847100"
  },
  {
    "code": "214150",
    "name": "클래시스",
    "amount": "1045.00",
    "price": "39396500",
    "ratio": "8.33",
    "totalPrice": "39553250"
  },
  {
    "code": "287410",
    "name": "제이시스메디칼",
    "amount": "3225.00",
    "price": "34056000",
    "ratio": "7.20",
    "totalPrice": "34056000"
  },
  {
    "code": "060280",
    "name": "큐렉소",
    "amount": "1753.00",
    "price": "31483880",
    "ratio": "6.66",
    "totalPrice": "31992250"
  },
  {
    "code": "069620",
    "name": "대웅제약",
    "amount": "273.00",
    "price": "29702400",
    "ratio": "6.28",
    "totalPrice": "29620500"
  },
  {
    "code": "336570",
    "name": "원텍",
    "amount": "2570.00",
    "price": "24929000",
    "ratio": "5.27",
    "totalPrice": "25160300"
  },
  {
    "code": "335890",
    "name": "비올",
    "amount": "2207.00",
    "price": "18450520",
    "ratio": "3.90",
    "totalPrice": "18340170"
  },
  {
    "code": "099430",
    "name": "바이오플러스",
    "amount": "2407.00",
    "price": "16126900",
    "ratio": "3.41",
    "totalPrice": "15886200"
  },
  {
    "code": "228670",
    "name": "레이",
    "amount": "673.00",
    "price": "15209800",
    "ratio": "3.22",
    "totalPrice": "14637750"
  },
  {
    "code": "214680",
    "name": "디알텍",
    "amount": "4003.00",
    "price": "14711025",
    "ratio": "3.11",
    "totalPrice": "14911175"
  },
  {
    "code": "043150",
    "name": "바텍",
    "amount": "424.00",
    "price": "13737600",
    "ratio": "2.90",
    "totalPrice": "13652800"
  },
  {
    "code": "200670",
    "name": "휴메딕스",
    "amount": "361.00",
    "price": "12580850",
    "ratio": "2.66",
    "totalPrice": "12616950"
  },
  {
    "code": "039840",
    "name": "디오",
    "amount": "561.00",
    "price": "12454200",
    "ratio": "2.63",
    "totalPrice": "12257850"
  },
  {
    "code": "216080",
    "name": "제테마",
    "amount": "764.00",
    "price": "11872560",
    "ratio": "2.51",
    "totalPrice": "11681560"
  },
  {
    "code": "038290",
    "name": "마크로젠",
    "amount": "545.00",
    "price": "11581250",
    "ratio": "2.45",
    "totalPrice": "11090750"
  },
  {
    "code": "KRD010010001",
    "name": "원화현금",
    "amount": "",
    "price": "1280606",
    "ratio": "0.27",
    "totalPrice": ""
  }
]