[
  {
    "code": "BMG0171K1018",
    "name": "ALIBABA HEALTH INFO",
    "amount": "7750.00",
    "price": "",
    "ratio": "",
    "totalPrice": ""
  },
  {
    "code": "KYG017191142",
    "name": "Alibaba group holding ltd",
    "amount": "2575.00",
    "price": "",
    "ratio": "",
    "totalPrice": ""
  },
  {
    "code": "KYG070341048",
    "name": "BIDU",
    "amount": "1000.00",
    "price": "",
    "ratio": "",
    "totalPrice": ""
  },
  {
    "code": "KYG1098A1013",
    "name": "BILIBILI",
    "amount": "383.00",
    "price": "",
    "ratio": "",
    "totalPrice": ""
  },
  {
    "code": "HK0285041858",
    "name": "BYD ELECTRONIC INTL CO LTD",
    "amount": "1125.00",
    "price": "",
    "ratio": "",
    "totalPrice": ""
  },
  {
    "code": "KYG2121R1039",
    "name": "CHINA LITERATURE",
    "amount": "650.00",
    "price": "",
    "ratio": "",
    "totalPrice": ""
  },
  {
    "code": "KYG3902L1095",
    "name": "GDS HOLDINGS LTD-CL A",
    "amount": "563.00",
    "price": "",
    "ratio": "",
    "totalPrice": ""
  },
  {
    "code": "CNE1000048K8",
    "name": "HAIER SMART HOME CO LTD-H",
    "amount": "3450.00",
    "price": "",
    "ratio": "",
    "totalPrice": ""
  },
  {
    "code": "HCTX3INDEX00",
    "name": "HSTECH F2311",
    "amount": "1.00",
    "price": "",
    "ratio": "",
    "totalPrice": ""
  },
  {
    "code": "HK0000218211",
    "name": "HUA HONG SEMI",
    "amount": "875.00",
    "price": "",
    "ratio": "",
    "totalPrice": ""
  },
  {
    "code": "KYG5074A1004",
    "name": "JD HEALTH INT",
    "amount": "1569.00",
    "price": "",
    "ratio": "",
    "totalPrice": ""
  },
  {
    "code": "KYG8208B1014",
    "name": "JD.COM",
    "amount": "1750.00",
    "price": "",
    "ratio": "",
    "totalPrice": ""
  },
  {
    "code": "KYG525681477",
    "name": "KINGDEE INT'L",
    "amount": "3875.00",
    "price": "",
    "ratio": "",
    "totalPrice": ""
  },
  {
    "code": "KYG5264Y1089",
    "name": "KINGSOFT",
    "amount": "1350.00",
    "price": "",
    "ratio": "",
    "totalPrice": ""
  },
  {
    "code": "KYG5313A1013",
    "name": "KOOLEARN",
    "amount": "688.00",
    "price": "",
    "ratio": "",
    "totalPrice": ""
  },
  {
    "code": "KYG532631028",
    "name": "Kuaishou Technology",
    "amount": "3413.00",
    "price": "",
    "ratio": "",
    "totalPrice": ""
  },
  {
    "code": "KYG5479M1050",
    "name": "LI AUTO",
    "amount": "1450.00",
    "price": "",
    "ratio": "",
    "totalPrice": ""
  },
  {
    "code": "HK0992009065",
    "name": "Lenovo Group Ltd",
    "amount": "11250.00",
    "price": "",
    "ratio": "",
    "totalPrice": ""
  },
  {
    "code": "KYG596691041",
    "name": "MEITUAN DIANPING",
    "amount": "1700.00",
    "price": "",
    "ratio": "",
    "totalPrice": ""
  },
  {
    "code": "KYG6427A1022",
    "name": "NETEASE",
    "amount": "1025.00",
    "price": "",
    "ratio": "",
    "totalPrice": ""
  },
  {
    "code": "KYG6525F1028",
    "name": "NIO INC",
    "amount": "69.00",
    "price": "",
    "ratio": "",
    "totalPrice": ""
  },
  {
    "code": "KYG711391022",
    "name": "PING AN HEALTHCARE AND TECHN",
    "amount": "875.00",
    "price": "",
    "ratio": "",
    "totalPrice": ""
  },
  {
    "code": "KYG8062L1041",
    "name": "SENSETIME GROUP INC-CLASS B",
    "amount": "26000.00",
    "price": "",
    "ratio": "",
    "totalPrice": ""
  },
  {
    "code": "KYG8020E1199",
    "name": "SMIC Equity",
    "amount": "5938.00",
    "price": "",
    "ratio": "",
    "totalPrice": ""
  },
  {
    "code": "KYG8586D1097",
    "name": "SUNNY OPTICAL TECH",
    "amount": "1013.00",
    "price": "",
    "ratio": "",
    "totalPrice": ""
  },
  {
    "code": "KYG875721634",
    "name": "TENCENT HOLD",
    "amount": "713.00",
    "price": "",
    "ratio": "",
    "totalPrice": ""
  },
  {
    "code": "KYG9066F1019",
    "name": "TRIP COM GROUP",
    "amount": "194.00",
    "price": "",
    "ratio": "",
    "totalPrice": ""
  },
  {
    "code": "KYG9515T1085",
    "name": "Weibo Corp",
    "amount": "3.00",
    "price": "",
    "ratio": "",
    "totalPrice": ""
  },
  {
    "code": "KYG9830T1067",
    "name": "XIAOMI CORP-CLASS B",
    "amount": "18900.00",
    "price": "",
    "ratio": "",
    "totalPrice": ""
  },
  {
    "code": "KYG982AW1003",
    "name": "Xpeng inc",
    "amount": "1713.00",
    "price": "",
    "ratio": "",
    "totalPrice": ""
  },
  {
    "code": "CNE100002QY7",
    "name": "ZHONGAN ONLINE P&C INSURANCE",
    "amount": "1200.00",
    "price": "",
    "ratio": "",
    "totalPrice": ""
  },
  {
    "code": "KRD010010001",
    "name": "원화현금",
    "amount": "",
    "price": "102078150",
    "ratio": "",
    "totalPrice": ""
  },
  {
    "code": "CASH00000001",
    "name": "설정현금액",
    "amount": "",
    "price": "569898582",
    "ratio": "",
    "totalPrice": ""
  }
]