[
  {
    "code": "160580",
    "name": "TIGER 구리실물",
    "amount": "14333.00",
    "price": "141753370",
    "ratio": "",
    "totalPrice": "141896700"
  },
  {
    "code": "ALG4_21",
    "name": "ALUMINIUM 3MO ($) (LME) FEB 024",
    "amount": "3.00",
    "price": "",
    "ratio": "",
    "totalPrice": "231048570"
  },
  {
    "code": "CUG4_21",
    "name": "COPPER 3MO ($) (LME) FEB 024",
    "amount": "0.50",
    "price": "",
    "ratio": "",
    "totalPrice": "138630768"
  },
  {
    "code": "LNG4_21",
    "name": "NICKEL 3MO ($) (LME) FEB 024",
    "amount": "0.33",
    "price": "",
    "ratio": "",
    "totalPrice": "42536851"
  },
  {
    "code": "KR4175V10001",
    "name": "미국달러 F 202401",
    "amount": "-5.50",
    "price": "",
    "ratio": "",
    "totalPrice": "-71500000"
  },
  {
    "code": "KRD010010001",
    "name": "원화현금",
    "amount": "",
    "price": "425918178",
    "ratio": "",
    "totalPrice": ""
  },
  {
    "code": "CASH00000001",
    "name": "설정현금액",
    "amount": "",
    "price": "567814878",
    "ratio": "",
    "totalPrice": ""
  }
]