[
  {
    "code": "143850",
    "name": "TIGER 미국S&P500선물(H)",
    "amount": "1710.00",
    "price": "92151900",
    "ratio": "",
    "totalPrice": "91929600"
  },
  {
    "code": "US78462F1030",
    "name": "SPDR S&P 500 ETF TRUST",
    "amount": "23.00",
    "price": "",
    "ratio": "",
    "totalPrice": "14158483"
  },
  {
    "code": "KRYZTRSC4N06",
    "name": "미국S&P500 TRS(미래에셋증권)",
    "amount": "4940780.17",
    "price": "",
    "ratio": "",
    "totalPrice": "4940780"
  },
  {
    "code": "KRYZTRSC4N05",
    "name": "미국S&P500 TRS(한국투자증권)",
    "amount": "89163440.36",
    "price": "",
    "ratio": "",
    "totalPrice": "89163440"
  },
  {
    "code": "KRD010010001",
    "name": "원화현금",
    "amount": "",
    "price": "443005943",
    "ratio": "",
    "totalPrice": ""
  },
  {
    "code": "CASH00000001",
    "name": "설정현금액",
    "amount": "",
    "price": "643198246",
    "ratio": "",
    "totalPrice": ""
  }
]