[
  {
    "code": "US37954Y4834",
    "name": "GLOBAL X NASD 100 COV CALL",
    "amount": "2869.98",
    "price": "",
    "ratio": "",
    "totalPrice": "63304827"
  },
  {
    "code": "US46090E1038",
    "name": "INVESCO QQQ TRUST SERIES 1",
    "amount": "17.28",
    "price": "",
    "ratio": "",
    "totalPrice": "8699948"
  },
  {
    "code": "KRYZTRSD9L05",
    "name": "나스닥100커버드콜 TRS 230920-05",
    "amount": "16115135.02",
    "price": "",
    "ratio": "",
    "totalPrice": "16115135"
  },
  {
    "code": "KRYZTRSD9L06",
    "name": "나스닥100커버드콜 TRS 230920-06",
    "amount": "5646684.42",
    "price": "",
    "ratio": "",
    "totalPrice": "5646684"
  },
  {
    "code": "KRYZTRSD9L07",
    "name": "나스닥100커버드콜 TRS 230920-07",
    "amount": "9204045.81",
    "price": "",
    "ratio": "",
    "totalPrice": "9204045"
  },
  {
    "code": "KRYZTRSD9M02",
    "name": "나스닥100커버드콜 TRS 230921-02",
    "amount": "19775922.47",
    "price": "",
    "ratio": "",
    "totalPrice": "19775922"
  },
  {
    "code": "KRYZTRSDB101",
    "name": "나스닥100커버드콜 TRS 231101-01",
    "amount": "27638903.27",
    "price": "",
    "ratio": "",
    "totalPrice": "27638903"
  },
  {
    "code": "KRYZTRSDBD01",
    "name": "나스닥100커버드콜 TRS 231113-01",
    "amount": "114560616.36",
    "price": "",
    "ratio": "",
    "totalPrice": "114560616"
  },
  {
    "code": "KRYZTRSDBL01",
    "name": "나스닥100커버드콜 TRS 231120-01",
    "amount": "41593780.87",
    "price": "",
    "ratio": "",
    "totalPrice": "41593780"
  },
  {
    "code": "KRYZTRSDBN01",
    "name": "나스닥100커버드콜 TRS 231122-01",
    "amount": "133943149.19",
    "price": "",
    "ratio": "",
    "totalPrice": "133943149"
  },
  {
    "code": "KRD010010001",
    "name": "원화현금",
    "amount": "",
    "price": "37939103",
    "ratio": "",
    "totalPrice": ""
  },
  {
    "code": "CASH00000001",
    "name": "설정현금액",
    "amount": "",
    "price": "478422112",
    "ratio": "",
    "totalPrice": ""
  }
]